passmanager_jsv/__init__.py
passmanager_jsv/passwd_manager.py
passwordManager_jsv-0.0.2.dist-info/METADATA
passwordManager_jsv-0.0.2.dist-info/WHEEL
passwordManager_jsv-0.0.2.dist-info/entry_points.txt
passwordManager_jsv-0.0.2.dist-info/top_level.txt
passwordManager_jsv-0.0.2.dist-info/RECORD
