Metadata-Version: 2.1
Name: passwordManager_jsv
Version: 0.0.2
Author: Sahaya Valan J
Author-email: sahayavalanj1@gmail.com
